brew_migrator/__init__.py
brew_migrator/cli.py
brew_migrator/core/brew.py
brew_migrator/core/history.py
brew_migrator/ui/console.py
brew_migrator-0.0.2.dist-info/licenses/LICENSE
brew_migrator-0.0.2.dist-info/METADATA
brew_migrator-0.0.2.dist-info/WHEEL
brew_migrator-0.0.2.dist-info/entry_points.txt
brew_migrator-0.0.2.dist-info/top_level.txt
brew_migrator-0.0.2.dist-info/RECORD
