Metadata-Version: 2.4
Name: brew-migrator
Version: 0.0.2
Summary: Migrate applications from /Applications to Homebrew Casks
Author-email: Christopher Zimbizi <chriszimbizi@gmail.com>
License: # The MIT License (MIT)
Project-URL: Homepage, https://github.com/chriszimbizi/brew-migrator
Project-URL: Repository, https://github.com/chriszimbizi/brew-migrator
Project-URL: Bug Tracker, https://github.com/chriszimbizi/brew-migrator/issues
Project-URL: Author Website, https://www.chriszimbizi.com/
Keywords: homebrew,mac,migration,cask
Classifier: Programming Language :: Python :: 3
Classifier: License :: OSI Approved :: MIT License
Classifier: Operating System :: MacOS :: MacOS X
Classifier: Environment :: Console
Classifier: Topic :: Utilities
Requires-Python: >=3.8
License-File: LICENSE
Dynamic: license-file
